{
  "capturedAt": "2026-04-13T21:37:05.369Z",
  "cmaId": "52059",
  "cmaName": "109 Morningside st",
  "subjectMls": "2022012769",
  "compTableHeader": [
    "",
    "",
    "ID",
    "DisplayId",
    "Picture Count",
    "MLS#",
    "Class",
    "Property Type",
    "Area",
    "Price",
    "Address",
    "City",
    "State",
    "Zip",
    "Status",
    "Price Per SQFT",
    "List Price/SqFt Liv",
    "Sold Price/LvSqFt",
    "SqFt Living",
    "row_highlight"
  ],
  "comps": [
    {
      "mlsNumber": "2025008366",
      "address": "107 LEJEUNE ST",
      "city": "New Roads",
      "state": "LA",
      "propertyClass": "Residential",
      "propertyType": "Detached Single Family",
      "area": "PC MLS Area 74",
      "price": 341885,
      "beds": null,
      "baths": null,
      "sqft": 1220,
      "dom": null,
      "status": "Closed",
      "rawCells": [
        "1",
        "",
        "2025008366:0",
        "2025008366",
        "23",
        "2025008366",
        "Residential",
        "Detached Single Family",
        "PC MLS Area 74",
        "$341,885",
        "107 LEJEUNE ST",
        "New Roads",
        "LA",
        "70760",
        "Closed",
        "$280.23",
        "286.89",
        "280.23",
        "1,220",
        "statusColor2"
      ]
    },
    {
      "mlsNumber": "2025006949",
      "address": "205 OLINDE ST",
      "city": "New Roads",
      "state": "LA",
      "propertyClass": "Residential",
      "propertyType": "Detached Single Family",
      "area": "PC MLS Area 74",
      "price": 232000,
      "beds": null,
      "baths": null,
      "sqft": 1512,
      "dom": null,
      "status": "Closed",
      "rawCells": [
        "2",
        "",
        "2025006949:0",
        "2025006949",
        "15",
        "2025006949",
        "Residential",
        "Detached Single Family",
        "PC MLS Area 74",
        "$232,000",
        "205 OLINDE ST",
        "New Roads",
        "LA",
        "70760",
        "Closed",
        "$153.44",
        "157.41",
        "153.44",
        "1,512",
        "statusColor2"
      ]
    },
    {
      "mlsNumber": "2024020556",
      "address": "311 PENNSYLVANIA AVE",
      "city": "New Roads",
      "state": "LA",
      "propertyClass": "Residential",
      "propertyType": "Detached Single Family",
      "area": "PC MLS Area 74",
      "price": 220000,
      "beds": null,
      "baths": null,
      "sqft": 1658,
      "dom": null,
      "status": "Closed",
      "rawCells": [
        "3",
        "",
        "2024020556:0",
        "2024020556",
        "32",
        "2024020556",
        "Residential",
        "Detached Single Family",
        "PC MLS Area 74",
        "$220,000",
        "311 PENNSYLVANIA AVE",
        "New Roads",
        "LA",
        "70760",
        "Closed",
        "$132.69",
        "138.66",
        "132.69",
        "1,658",
        "statusColor2"
      ]
    },
    {
      "mlsNumber": "2025004233",
      "address": "505 WESTEND",
      "city": "New Roads",
      "state": "LA",
      "propertyClass": "Residential",
      "propertyType": "Detached Single Family",
      "area": "PC MLS Area 74",
      "price": 157000,
      "beds": null,
      "baths": null,
      "sqft": 963,
      "dom": null,
      "status": "Closed",
      "rawCells": [
        "4",
        "",
        "2025004233:0",
        "2025004233",
        "17",
        "2025004233",
        "Residential",
        "Detached Single Family",
        "PC MLS Area 74",
        "$157,000",
        "505 WESTEND",
        "New Roads",
        "LA",
        "70760",
        "Closed",
        "$163.03",
        "165.63",
        "163.03",
        "963",
        "statusColor2"
      ]
    },
    {
      "mlsNumber": "2024019160",
      "address": "602 Berthier Street",
      "city": "New Roads",
      "state": "LA",
      "propertyClass": "Residential",
      "propertyType": "Detached Single Family",
      "area": "PC MLS Area 74",
      "price": 150000,
      "beds": null,
      "baths": null,
      "sqft": 1281,
      "dom": null,
      "status": "Closed",
      "rawCells": [
        "5",
        "",
        "2024019160:0",
        "2024019160",
        "13",
        "2024019160",
        "Residential",
        "Detached Single Family",
        "PC MLS Area 74",
        "$150,000",
        "602 Berthier Street",
        "New Roads",
        "LA",
        "70760",
        "Closed",
        "$117.10",
        "124.90",
        "117.10",
        "1,281",
        "statusColor2"
      ]
    },
    {
      "mlsNumber": "2025018755",
      "address": "807 JANIS ST",
      "city": "New Roads",
      "state": "LA",
      "propertyClass": "Residential",
      "propertyType": "Detached Single Family",
      "area": "PC MLS Area 74",
      "price": 145000,
      "beds": null,
      "baths": null,
      "sqft": 1091,
      "dom": null,
      "status": "Closed",
      "rawCells": [
        "6",
        "",
        "2025018755:0",
        "2025018755",
        "10",
        "2025018755",
        "Residential",
        "Detached Single Family",
        "PC MLS Area 74",
        "$145,000",
        "807 JANIS ST",
        "New Roads",
        "LA",
        "70760",
        "Closed",
        "$132.91",
        "137.49",
        "132.91",
        "1,091",
        "statusColor2"
      ]
    }
  ]
}